artfornormies/__init__.py
artfornormies/functions.py
artfornormies/object_graphs.py
artfornormies-0.0.5.dist-info/licenses/LICENSE
artfornormies-0.0.5.dist-info/METADATA
artfornormies-0.0.5.dist-info/WHEEL
artfornormies-0.0.5.dist-info/top_level.txt
artfornormies-0.0.5.dist-info/RECORD
