Metadata-Version: 2.4
Name: artfornormies
Version: 0.0.5
Summary: For generating personal reminders as data visualizations (venn, bar, heatmap, scatter, etc)
Home-page: https://github.com/jon-tk-chan/artfornormies
Author: Jonathan Chan
Author-email: jonathan.chan41@gmail.com
Classifier: Programming Language :: Python :: 3
Classifier: License :: OSI Approved :: MIT License
Classifier: Operating System :: OS Independent
Requires-Python: >=3.7
License-File: LICENSE
Requires-Dist: plotly==5.10.0
Dynamic: license-file
